Metadata-Version: 2.1
Name: welford-remove
Version: 0.1
Summary: Python (numpy) implementation of Welford's algorithm with the ability to remove data points.
Home-page: https://github.com/18goldr/welford-with-remove
Author: Robert Gold
Author-email: 18goldr@gmail.com
License: MIT
Keywords: statistics,online,welford
License-File: LICENSE
